mirk/__init__.py
mirk/providers_cv.py
mirk/providers_vlm.py
mirk-0.1.1.dist-info/LICENSE
mirk-0.1.1.dist-info/METADATA
mirk-0.1.1.dist-info/WHEEL
mirk-0.1.1.dist-info/RECORD
