Metadata-Version: 2.1
Name: mirk
Version: 0.1.1
Summary: Mirk is a vision-reasoning pipeline designed to interpret scenes only when needed.
Home-page: https://github.com/CuriousDima/mirk
License: MIT
Keywords: vision,ai,reasoning
Author: Dima Timofeev
Author-email: dimkat@gmail.com
Requires-Python: >=3.11,<4.0
Classifier: License :: OSI Approved :: MIT License
Classifier: Programming Language :: Python :: 3
Classifier: Programming Language :: Python :: 3.11
Classifier: Programming Language :: Python :: 3.12
Classifier: Programming Language :: Python :: 3.13
Requires-Dist: black (>=24.10.0,<25.0.0)
Requires-Dist: openai (>=1.12.0,<2.0.0)
Requires-Dist: opencv-python (>=4.9.0,<5.0.0)
Requires-Dist: python-dotenv (>=1.0.1,<2.0.0)
Requires-Dist: torch (==2.2.1)
Requires-Dist: ultralytics (>=8.1.28,<9.0.0)
Project-URL: Repository, https://github.com/CuriousDima/mirk
